pyelectroluxconnect/Session.py
pyelectroluxconnect/__init__.py
pyelectroluxconnect/certificatechain.pem
pyelectroluxconnect/urls.py
pyelectroluxconnect-0.3.20.dist-info/LICENSE
pyelectroluxconnect-0.3.20.dist-info/METADATA
pyelectroluxconnect-0.3.20.dist-info/WHEEL
pyelectroluxconnect-0.3.20.dist-info/top_level.txt
pyelectroluxconnect-0.3.20.dist-info/RECORD
