Metadata-Version: 2.1
Name: pyelectroluxconnect
Version: 0.3.20
Summary: Interface for Electrolux Connectivity Platform API
Home-page: https://github.com/tomeko12/pyelectroluxconnect
Author: tomeko
License: Apache Software License
Keywords: home automation electrolux aeg frigidaire husqvarna
Classifier: Programming Language :: Python :: 3.10
Classifier: License :: OSI Approved :: Apache Software License
Classifier: Operating System :: OS Independent
Classifier: Topic :: Home Automation
Classifier: Development Status :: 4 - Beta
License-File: LICENSE
Requires-Dist: requests >=2.20.0
Requires-Dist: beautifulsoup4 <5,>=4
